<?xml version="1.0" encoding="UTF-8"?>
<!DOCTYPE transcription SYSTEM "http://www.livesandletters.ac.uk/schema/aor_20141023.dtd">

<transcription xmlns:xsi="http://www.w3.org/2001/XMLSchema-instance"
    xsi:noNamespaceSchemaLocation="http://www.livesandletters.ac.uk/schema/aor2_18112016.xsd">
    <page filename="036.tif" reader="John Dee" pagination="13" signature="b"/>
    <annotation>
        
        <marginalia hand="English_secretary" anchor_text="de coloribus scilicet hominum, ac moribus">
            <language ident="LA">
                <position place="right_margin" book_orientation="0">
                    <marginalia_text>
                        De coloribus ho[m]i[n]um et moribus
                    </marginalia_text>
                </position>
            </language>
            <translation>
                On the colour of men and customs.
            </translation>
        </marginalia>
        
        <underline method="pen" type="straight" language="LA" text="omnibus animantibus, quae terrena congregatione gignu[n]tur, uiuendi"/>
        <underline method="pen" type="straight" language="LA" text="necessitatis ineuitabili sententia contineri. Cedamus"/>
        <underline method="pen" type="straight" language="LA" text="corusci solis incensa luminibus, &amp; sempiterni ardoris adustione torrida"/>
        
        <mark name="bracket" method="pen" place="right_margin"/>
        <mark name="vertical_bar" method="pen" place="right_margin" colour="red"/>
        
    </annotation>
</transcription>