<?xml version="1.0" encoding="UTF-8"?> 
<!DOCTYPE transcription SYSTEM "http://www.livesandletters.ac.uk/schema/aor_20141023.dtd">

<transcription xmlns:xsi="http://www.w3.org/2001/XMLSchema-instance"
    xsi:noNamespaceSchemaLocation="http://www.livesandletters.ac.uk/schema/aor2_18112016.xsd">
    <page filename="0366.tif" reader="John Dee" pagination="338" signature="[yy.i.[v]]"/>
    <annotation>
        
        <marginalia hand="English_secretary">
            <language ident="LA">
                <position place="left_margin" book_orientation="0">
                    <marginalia_text>
                        insultare veheme[n]tius
                    </marginalia_text>
                </position>
            </language>
            <translation>
                To insult very harshly.
            </translation>
        </marginalia>
        
        <marginalia hand="English_secretary" anchor_text="speluncas">
            <language ident="LA">
                <position place="left_margin" book_orientation="0">
                    <marginalia_text>
                        spelunca
                    </marginalia_text>
                    <location name="Sperlonga"/>
                </position>
            </language>
            <translation>
                Sperlonga.
            </translation>
        </marginalia>
        
        <marginalia hand="English_secretary" anchor_text="cuiusquemodi">
            <language ident="LA">
                <position place="left_margin" book_orientation="0">
                    <marginalia_text>
                        Cuiusquemodi
                    </marginalia_text>
                </position>
            </language>
            <translation>
                Of whatever kind.
            </translation>
        </marginalia>
        
        <marginalia hand="English_secretary" anchor_text="qui mortalis">
            <language ident="LA">
                <position place="left_margin" book_orientation="0">
                    <marginalia_text>
                        qui mortalis
                    </marginalia_text>
                </position>
            </language>
            <translation>
                The mortals.
            </translation>
        </marginalia>
        
        <marginalia hand="English_secretary" anchor_text="Phrygi, qui arborem fici nu[m]quam vidisset, fiscina[m] ficoru[m]">
            <language ident="LA">
                <position place="left_margin" book_orientation="0">
                    <marginalia_text>
                        Phrix arbore[m] fici nu[m]qua[m] vidit
                    </marginalia_text>
                </position>
            </language>
            <translation>
                A Phrygian [who] had never seen a fig-tree [Loeb 324, 487].
            </translation>
        </marginalia>
        
        <marginalia hand="English_secretary" anchor_text="fiscina[m] ficoru[m]">
            <language ident="LA">
                <position place="left_margin" book_orientation="0">
                    <marginalia_text>
                        fiscina[m] ficoru[m]
                    </marginalia_text>
                </position>
            </language>
            <translation>
                A basket of figs.
            </translation>
        </marginalia>
        
        <marginalia hand="English_secretary" anchor_text="colume[n] actionis">
            <language ident="LA">
                <position place="left_margin" book_orientation="0">
                    <marginalia_text>
                        colume[n] actio[n]is
                    </marginalia_text>
                </position>
            </language>
            <translation>
                Pillar of action.
            </translation>
        </marginalia>
        
        <marginalia hand="English_secretary" anchor_text="disseruit &amp; subtiliter &amp; copiose">
            <language ident="LA">
                <position place="left_margin" book_orientation="0">
                    <marginalia_text>
                        disserere subtilit[er]] copiose
                    </marginalia_text>
                </position>
            </language>
            <translation>
                To speak in detail and in length.
            </translation>
        </marginalia>
        
        <marginalia hand="English_secretary" anchor_text="persalutet">
            <language ident="LA">
                <position place="left_margin" book_orientation="0">
                    <marginalia_text>
                        persalutare
                    </marginalia_text>
                </position>
            </language>
            <translation>
                To greet.
            </translation>
        </marginalia>
        
        <underline method="pen" type="straight" language="LA" text="putarem, vociferarer, &amp; qua[n]tum maxime possem, contendere[m], testarer publicanos, excitarem negotiatores, 
            vestram etiam conscientiam implorarem: caera deprehensa, confiderem totius testimonii fictam audaciam manifesto comprehe[n]sam, atque oppressam teneri. Nunc vero non insultabo vehementius, 
            nec volitabo in hoc insolentius, neque in istum nugatorem ta[m]quam in aliquem testem inuehar, neque in toto AEmone[n]sium testimonio: siue hic confictum est, vt apparet: siue missum domo est, vt dicitur, 
            co[m]mouebor. etenim quibus ego istam laudationem remittam, quonia[m] (vt Asclepiades dicit) leues, horum testimoniu[m] no[n] pertimescam"/>
        <underline method="pen" type="straight" language="LA" text="quiescant igitur, &amp; me hoc in lucro ponere, atque aliud agere patiantur"/>
        <underline method="pen" type="straight" language="LA" text="cuiusquemodi"/>
        <underline method="pen" type="straight" language="LA" text="qui mortalis esset"/>
        <underline method="pen" type="straight" language="LA" text="locuples testis doloris &amp; sanguinis sui non fuerit, idem sit grauis author iniuriae publicae"/>
        <underline method="pen" type="straight" language="LA" text="fiscina[m] ficoru[m]"/>
        <underline method="pen" type="straight" language="LA" text="edacem enim hospitem"/>
        <underline method="pen" type="straight" language="LA" text="mortuus est aculeo iam dimisso"/>
        <underline method="pen" type="straight" language="LA" text="actionis tuae Mithridates"/>
        <underline method="pen" type="straight" language="LA" text="reprehe[n]sus, co[n]uictus, fract&uacute;sque"/>
        <underline method="pen" type="straight" language="LA" text="nos vt instituimus, ad"/>
        <underline method="pen" type="straight" language="LA" text="pergamus"/>
        <underline method="pen" type="straight" language="LA" text="homo ineptus &amp; loquax"/>
        <underline method="pen" type="straight" language="LA" text="traditurum etia[m] caeteris profitebatur, ipse omnibus turpissimis iudiciis conuictus est"/>
        
        <mark name="bracket" method="pen" place="left_margin"/>
        <mark name="vertical_bar" method="pen" place="left_margin"/>
        
        <numeral place="left_margin">8</numeral>
        <numeral place="left_margin">10</numeral>
        <numeral place="left_margin">2</numeral>
        <numeral place="left_margin">3</numeral>
        <numeral place="left_margin">13</numeral>
        <numeral place="left_margin">16</numeral>
        <numeral place="left_margin">21</numeral>
        <numeral place="left_margin">18</numeral>
        <numeral place="left_margin">21</numeral>
        <numeral place="left_margin">12</numeral>
        <numeral place="left_margin">13</numeral>
        <numeral place="left_margin">21</numeral>
        <numeral place="left_margin">21</numeral>
  
    </annotation>
</transcription>