<?xml version="1.0" encoding="UTF-8"?>
<!DOCTYPE transcription SYSTEM "http://www.livesandletters.ac.uk/schema/aor_20141023.dtd">

<transcription xmlns:xsi="http://www.w3.org/2001/XMLSchema-instance"
    xsi:noNamespaceSchemaLocation="http://www.livesandletters.ac.uk/schema/aor2_18112016.xsd">
    <page filename="0529.tif" reader="John Dee" pagination="501" signature="iii.iii."/>
    <annotation>
        
        <marginalia hand="English_secretary" anchor_text="sempiternas foedissimae turpitudinis notas subieritis">
            <language ident="LA">
                <position place="right_margin" book_orientation="0">
                    <marginalia_text>
                        subire notas turpitudinis fo[e]diss[imae] sempiternas.
                    </marginalia_text>
                </position>
            </language>
            <translation>
                To mark 'with an indelible stigma of the deepest ignominy' [Loeb 252, 191].
            </translation>
        </marginalia>
        
        <marginalia hand="English_secretary" anchor_text="laceratione">
            <language ident="LA">
                <position place="right_margin" book_orientation="0">
                    <marginalia_text>
                        laceratio
                    </marginalia_text>
                </position>
            </language>
            <translation>
                Tearing.
            </translation>
        </marginalia>
        
        <marginalia hand="English_secretary" anchor_text="voluptarii Graeci">
            <language ident="LA">
                <position place="right_margin" book_orientation="0">
                    <marginalia_text>
                        voluptarij Gra[e]ci
                    </marginalia_text>
                </position>
            </language>
            <translation>
                Pleasant Greeks.
            </translation>
        </marginalia>
        
        <marginalia hand="English_secretary" anchor_text="flagitia ingurgitasses">
            <language ident="LA">
                <position place="right_margin" book_orientation="0">
                    <marginalia_text>
                        flagitia ingurgitare
                    </marginalia_text>
                </position>
            </language>
            <translation>
                Engulfed in shame.
            </translation>
        </marginalia>
        
        <marginalia hand="English_secretary" anchor_text="bonus, non beatus">
            <language ident="LA">
                <position place="right_margin" book_orientation="0">
                    <marginalia_text>
                        o[mn]is bonus, beatus.
                    </marginalia_text>
                </position>
            </language>
            <translation>
                A completely good and happy person.
            </translation>
        </marginalia>
        
        <marginalia hand="English_secretary" anchor_text="M. Regulus">
            <language ident="LA">
                <position place="right_margin" book_orientation="0">
                    <marginalia_text>
                        M Regulus
                    </marginalia_text>
                    <person name="Marcus Atilius Regulus"/>
                </position>
            </language>
            <translation>
                Marcus Atilius Regulus.
            </translation>
        </marginalia>
        
        <marginalia hand="English_secretary" anchor_text="C. Marius">
            <language ident="LA">
                <position place="right_margin" book_orientation="0">
                    <marginalia_text>
                        C Marius
                    </marginalia_text>
                    <person name="Gaius Marius"/>
                </position>
            </language>
            <translation>
                Gaius Marius.
            </translation>
        </marginalia>
        
        <marginalia hand="English_secretary">
            <language ident="LA">
                <position place="right_margin" book_orientation="0">
                    <marginalia_text>
                        Supplicium
                    </marginalia_text>
                </position>
            </language>
            <translation>
                Punishment.
            </translation>
        </marginalia>
        
        <marginalia hand="English_secretary">
            <language ident="LA">
                <position place="right_margin" book_orientation="0">
                    <marginalia_text>
                        quid.
                    </marginalia_text>
                </position>
            </language>
            <translation>
                What.
            </translation>
        </marginalia>
        
        <marginalia hand="English_secretary" anchor_text="preces">
            <language ident="LA">
                <position place="right_margin" book_orientation="0">
                    <marginalia_text>
                        PR&AElig;CES
                    </marginalia_text>
                </position>
            </language>
            <translation>
                Prayers.
            </translation>
        </marginalia>
        
        <marginalia hand="English_secretary" anchor_text="execratio">
            <language ident="LA">
                <position place="right_margin" book_orientation="0">
                    <marginalia_text>
                        Execratio
                    </marginalia_text>
                </position>
            </language>
            <translation>
                A curse.
            </translation>
        </marginalia>
        
        <marginalia hand="English_secretary" anchor_text="oculis fugiat, auribus respuat, animo aspernetur">
            <language ident="LA">
                <position place="right_margin" book_orientation="0">
                    <marginalia_text>
                        oculis fugere. aurib[us] respuere a[n]i[m]o aspernari
                    </marginalia_text>
                </position>
            </language>
            <translation>
                To flee from the eyes, to reject with the ears, to despise with the soul.
            </translation>
        </marginalia>
        
        <marginalia hand="English_secretary" anchor_text="expetiui, haec optaui, haec precatus">
            <language ident="LA">
                <position place="right_margin" book_orientation="0">
                    <marginalia_text>
                        expetere optare pr[a]ecari
                    </marginalia_text>
                </position>
            </language>
            <translation>
                To desire, to wish, to beware.
            </translation>
        </marginalia>
        
        <marginalia hand="English_secretary" anchor_text="accidit praeter optatum">
            <language ident="LA">
                <position place="right_margin" book_orientation="0">
                    <marginalia_text>
                        accidit p[rae]t[er] optatu[m]
                    </marginalia_text>
                </position>
            </language>
            <translation>
                It agrees with [my] wish.
            </translation>
        </marginalia>
        
        <marginalia hand="English_secretary">
            <language ident="LA">
                <position place="right_margin" book_orientation="0">
                    <marginalia_text>
                        Pen[a]e Malor[um]
                    </marginalia_text>
                </position>
            </language>
            <translation>
                Punishments of the bad.
            </translation>
        </marginalia>
        
        <marginalia hand="English_secretary">
            <language ident="LA">
                <position place="right_margin" book_orientation="0">
                    <marginalia_text>
                        Diuina Sente[n]tia
                    </marginalia_text>
                </position>
            </language>
            <translation>
                A divine judgement.
            </translation>
        </marginalia>
        
        <underline method="pen" type="straight" language="LA" text="quos vtinam ita audires vt erant audiendi"/>
        <underline method="pen" type="straight" language="LA" text="te in tot flagitia"/>
        <underline method="pen" type="straight" language="LA" text="Sed dicunt ipsi, qui mala dolore, bona voluptate definiunt"/>
        <underline method="pen" type="straight" language="LA" text="tantam virtutis esse vim voluerunt, vt no[n] posset vnquam esse vir bonus, non beatus"/>
        <underline method="pen" type="straight" language="LA" text="nisi nocenti, suscaepta fraus, impedita &amp; oppressa mens co[n]scientia, bonoru[m]"/>
        <underline method="pen" type="straight" language="LA" text="dii immortales meas preces audiueru[n]t"/>
        <underline method="pen" type="straight" language="LA" text="Thyestea ista execratio est, poetae vulgi animos, no[n] sapientu[m] mouentis"/>
        <underline method="pen" type="straight" language="LA" text="naufragio expulsus vspia[m] saxis fixus asperis euisceratus latere penderes (vt ait ille) saxa spargens tabo, sanie, sanguine atro"/>
        <underline method="pen" type="straight" language="LA" text="in fortuna quada[m] est illa mors, no[n] poena"/>
        <underline method="pen" type="straight" language="LA" text="non secus ac de teterrimis hostibus: qu&ograve;d"/>
        <underline method="pen" type="straight" language="LA" text="qui vos non oculis fugiat"/>
        <underline method="pen" type="straight" language="LA" text="immortalium has esse in impios &amp; consceleratos poenas certissimas constitutas"/>
        <underline method="pen" type="straight" language="LA" text="sua quenque fraus, suum facinus, suum scelus, sua audacia de sanitate ac me[n]te deturbat. hae sunt impioru[m] furiae, hae fla[m]mae, hae faces. 
            Ego te no[n] vecorde[m], no[n] furiosum, no[n] mente captum, non tragico illo Oreste, aut Athamante dementiorem"/>
        <underline method="pen" type="straight" language="LA" text="sis ausus prim&ugrave;m facere (na[m] is est caput) deinde paul&ograve; ant&egrave; Torquato grauissimo, &amp;"/>
        
        <mark name="bracket" method="pen" place="right_margin"/>
        <mark name="tripunctus_with_tail" method="pen" place="right_margin" language="LA" text="PR&AElig;CES"/>  
        <mark name="bracket" method="pen" place="right_margin"/>
        
        <numeral place="right_margin">18</numeral>
        <numeral place="right_margin">3</numeral>
        <numeral place="right_margin">21</numeral>
        <numeral place="right_margin">21</numeral>
        <numeral place="right_margin">21</numeral>
        
        <drawing type="florilegium" book_orientation="0" place="right_margin" method="pen" anchor_text="M Regulus"/>
        <drawing type="florilegium" book_orientation="0" place="right_margin" method="pen" anchor_text="C Marius"/>
        <drawing type="florilegium" book_orientation="0" place="right_margin" method="pen" anchor_text="Supplicinire quid"/>
        <drawing type="florilegium" book_orientation="0" place="right_margin" method="pen" anchor_text="Execratio"/>
        
        
    </annotation>
</transcription>