<?xml version="1.0" encoding="UTF-8"?>
<!DOCTYPE transcription SYSTEM "http://www.livesandletters.ac.uk/schema/aor_20141023.dtd">

<transcription xmlns:xsi="http://www.w3.org/2001/XMLSchema-instance"
    xsi:noNamespaceSchemaLocation="http://www.livesandletters.ac.uk/schema/aor2_18112016.xsd">
    <page filename="0736.tif" reader="John Dee" pagination="178" signature="[Mm.i.[v]]"/>   
    <annotation>
        
        <marginalia hand="Italian" anchor_text="Is ardentes faces intentat">
            <language ident="LA">
                <position place="left_margin" book_orientation="0">
                    <marginalia_text>
                        arde[n]tes inte[n]tare faces
                    </marginalia_text>
                </position>
            </language>
            <translation>
                To point burning torment.
            </translation>
        </marginalia>
        
        <marginalia hand="Italian" anchor_text="Dolor esse videtur acerrimus virtuti aduersarius">
            <language ident="LA">
                <position place="left_margin" book_orientation="0">
                    <marginalia_text>
                        Dolor acerrimus virtuti est aduersarius
                    </marginalia_text>
                </position>
            </language>
            <translation>
                The most severe pain is adverse to strength. 
            </translation>
        </marginalia>
        
        <marginalia hand="Italian" anchor_text="Pueri Spartiatae">
            <language ident="LA">
                <position place="left_margin" book_orientation="0">
                    <marginalia_text>
                        Pueri spartiata[e]
                    </marginalia_text>
                </position>
            </language>
            <translation>
                Boys from Sparta.
            </translation>
        </marginalia>
        
        <marginalia hand="Italian" anchor_text="India">
            <language ident="LA">
                <position place="left_margin" book_orientation="0">
                    <marginalia_text>
                        India
                    </marginalia_text>
                    <location name="India"/>
                </position>
            </language>
            <translation>
                India.
            </translation>
        </marginalia>
        
        <marginalia hand="Italian">
            <language ident="LA">
                <position place="left_margin" book_orientation="0">
                    <marginalia_text>
                        Gymnosophistae
                    </marginalia_text>
                </position>
            </language>
            <translation>
                Gymnosophists.
            </translation>
        </marginalia>
        
        <marginalia hand="Italian" anchor_text="Mulieres">
            <language ident="LA">
                <position place="left_margin" book_orientation="0">
                    <marginalia_text>
                        Mulieres viroru[m] ama[n]tes
                    </marginalia_text>
                </position>
            </language>
            <translation>
                Women love men.
            </translation>
        </marginalia>
        
        <marginalia hand="Italian" anchor_text="AEgyptiorum morem">
            <language ident="LA">
                <position place="left_margin" book_orientation="0">
                    <marginalia_text>
                        &AElig;gyptioru[m] mores
                    </marginalia_text>
                </position>
            </language>
            <translation>
                The customs of the Egyptians.
            </translation>
        </marginalia>
        
        <marginalia hand="Italian" anchor_text="bestiae">
            <language ident="LA">
                <position place="left_margin" book_orientation="0">
                    <marginalia_text>
                        Bestiaru[m] natura
                    </marginalia_text>
                </position>
            </language>
            <translation>
                The nature of beasts.
            </translation>
        </marginalia>
        
        <marginalia hand="Italian">
            <language ident="LA">
                <position place="left_margin" book_orientation="0">
                    <marginalia_text>
                        varia hominu[m] studia
                    </marginalia_text>
                </position>
            </language>
            <translation>
                Various pursuits of men.
            </translation>
        </marginalia>
        
        <marginalia hand="Italian">
            <language ident="LA">
                <position place="left_margin" book_orientation="0">
                    <marginalia_text>
                        Sapie[n]tis munus
                    </marginalia_text>
                </position>
            </language>
            <translation>
                The duty of the wise.
            </translation>
        </marginalia>
        
        <marginalia hand="Italian" anchor_text="nulla vincula impediunt vllius certae disciplinae">
            <language ident="LA">
                <position place="left_margin" book_orientation="0">
                    <marginalia_text>
                        Nulla vincula vllius disciplina[e] me impediunt
                    </marginalia_text>
                </position>
            </language>
            <translation>
                No chains prevent me from any discipline.
            </translation>
        </marginalia>
        
        <marginalia hand="Italian">
            <language ident="LA">
                <position place="left_margin" book_orientation="0">
                    <marginalia_text>
                        Sine retractione liber&egrave; dicere
                    </marginalia_text>
                </position>
            </language>
            <translation>
                To speak without free undertaking.
            </translation>
        </marginalia>
        
        <underline method="pen" type="straight" language="LA" text="superiorum dierum disputationibus armati &amp; parati"/>
        <underline method="pen" type="straight" language="LA" text="Is ardentes faces intentat"/>
        <underline method="pen" type="straight" language="LA" text="certantes pugnis, calcibus, vnguibus"/>
        <underline method="pen" type="straight" language="LA" text="vmbris, deliviis, otio, languore, desidia animum infecimus, opinionibus, mal&oacute;que more delinitum molliuimus"/>
        <underline method="pen" type="straight" language="LA" text="cernificinam pius subierint"/>
        <underline method="pen" type="straight" language="LA" text="montiuagos atque syluestres cursus lustration&eacute;sque patiuntur? No[n] pro suo partu ita prpugnant, 
            vt vulnera excipiant, nullos impetus, nullos ictus reformident"/>
        <underline method="pen" type="straight" language="LA" text="Plena vita exemplorum est, sed adhibeat oratio modum, &amp; redeat"/>
        <underline method="pen" type="straight" language="LA" text="deflexit"/>
        <underline method="pen" type="straight" language="LA" text="Quid enim ea foedius"/>
        <underline method="pen" type="straight" language="LA" text="tergiuersari non"/>
        <underline method="pen" type="straight" language="LA" text="proprium nihil quod poenitere possit, facere, nihil inuitum"/>
        <underline method="pen" type="straight" language="LA" text="grauiter, honeste omnia"/>
        <underline method="pen" type="straight" language="LA" text="nihil ita expectare, quasi certo futurum"/>
        <underline method="pen" type="straight" language="LA" text="quae fortissime de beata vita dici"/>
        <underline method="pen" type="straight" language="LA" text="vincula impediunt vllius certae disciplinae"/>
        <underline method="pen" type="straight" language="LA" text="retractione"/>
        
        <symbol name="Jupiter" place="left_margin"/>
        <symbol name="Jupiter" place="left_margin"/>
        <symbol name="Jupiter" place="left_margin"/>
        <symbol name="Jupiter" place="left_margin"/>
        
        <mark name="bracket" method="pen" place="left_margin"/>
        <mark name="bracket" method="pen" place="left_margin"/>
        <mark name="plus_sign" method="pen" place="left_margin"/>
        <mark name="plus_sign" method="pen" place="tail"/>
        
        <numeral place="left_margin">12</numeral>
        <numeral place="left_margin">21</numeral>
        <numeral place="left_margin">21</numeral>
        <numeral place="left_margin">12</numeral>

        <drawing type="florilegium" book_orientation="0" place="left_margin" method="pen"></drawing>
        <drawing type="florilegium" book_orientation="0" place="left_margin" method="pen"></drawing>
        <drawing type="florilegium" book_orientation="0" place="left_margin" method="pen"></drawing>
        
    </annotation>
</transcription>