<?xml version="1.0" encoding="UTF-8"?>
<!DOCTYPE transcription SYSTEM "http://www.livesandletters.ac.uk/schema/aor_20141023.dtd">

<transcription xmlns:xsi="http://www.w3.org/2001/XMLSchema-instance"
    xsi:noNamespaceSchemaLocation="http://www.livesandletters.ac.uk/schema/aor2_18112016.xsd">
    <page filename="434.tif" reader="John Dee" pagination="416" signature="[Nn.iij[v]]"/>
    <annotation>
        
        <underline method="pen" type="straight" language="LA" text="Valentini rapti sunt filij comitis Marchiae &amp; abducti"/>
        <underline method="pen" type="straight" language="LA" text="de castro de VVyndersor, faber"/>
        <underline method="pen" type="straight" language="LA" text="ingressus ad eos, truncatione manuu[m] atq[ue] capitis est mulctatus"/>
        <underline method="pen" type="straight" language="LA" text="ad Ovvenum Glendor cum filio octenni"/>
        
        <mark name="scribble" method="pen" place="left_margin"/>
        
    </annotation>
</transcription>

