<?xml version="1.0" encoding="UTF-8"?>

<!DOCTYPE transcription SYSTEM "http://www.livesandletters.ac.uk/schema/aor_20141023.dtd">

<transcription xmlns:xsi="http://www.w3.org/2001/XMLSchema-instance"
    xsi:noNamespaceSchemaLocation="http://www.livesandletters.ac.uk/schema/aor2_18112016.xsd">
    <page filename="c_120_b_4_(2)_f041r.tif" reader="John Dee" pagination="41" signature="K"/> 
    <annotation>
        
        <marginalia hand="Italian" anchor_text="substantia agens in hoc toto mu[n]do est unum [scilicet] Calor" method="pen">
            <language ident="LA">
                <position place="right_margin" book_orientation="0">
                    <marginalia_text>
                        Solus Calor est Agens in hoc mundo
                    </marginalia_text>
                </position>
            </language>
            <translation>
                Heat alone is the agent in this world.
            </translation>
        </marginalia>
        
        <marginalia hand="Italian" anchor_text="Et est calidus &amp; siccus in quarto" method="pen">
            <language ident="LA">
                <position place="right_margin" book_orientation="0">
                    <marginalia_text>
                        Calidus et siccus in 4&o_super;                    
                    </marginalia_text>
                </position>
            </language>
            <translation>
                Hot and dry in the fourth.
            </translation>
        </marginalia>
        
        <marginalia hand="Italian" anchor_text="72">
            <language ident="LA">
                <position place="intext" book_orientation="0">
                    <marginalia_text>
                        {Im&ograve; summa est 83: sed putandum est hoc no[n] latuisse 
                        authorem: Ip[su]m tame[n] numeru[m] suu[m] mysteriu[m] nobis obijcere 
                        ante oculos: hocq[ue] nome[n] mysticu[m] cum suis numeris, proposito bene q[ua]drare
                    </marginalia_text>
                </position>
            </language>
            <translation>
                On the contrary, the highest point is 83. But it must be believed that the author had not hidden this. Nevertheless [it must be believed that he cast his mystic
                number before our eyes: and that he made the mystical name suitable with his numbers, having related it well.
            </translation>
        </marginalia>
        
        <underline method="pen" type="grid" language="LA" text="mistam"/>
        <underline method="pen" type="straight" language="LA" text="Calore enim sublato nullus omnino Motus est"/>
        
        <table type="standard_table" place="intext">
            <tr>
                <th>Reso[lutio]</th>
            </tr>
            <tr>
                <td>&Sun;</td>
                <td>&Moon;</td>
            </tr>
            <tr>
                <td>41</td>
                <td>42</td>
            </tr>
            <tr>
                <th>Project[io]</th>
            </tr>
            <tr>
                <td>&Sun;</td>
                <td>&Moon;</td>
                <td>[Hieroglyphic Monad]</td>
            </tr>
            <tr>
                <td>41</td>
                <td>19</td>
                <td>13</td>
            </tr>
            <text hand="English_secretary" language="LA">vel potius</text>
            <translation>Dissolution. Or rather. Transmutation.</translation> <!--JG: Unsure about the transcription and translation of the words 'Reso' and 'Project'-->
        </table>
        
    </annotation>
</transcription>