<?xml version="1.0" encoding="UTF-8"?>
<!DOCTYPE transcription SYSTEM "http://www.livesandletters.ac.uk/schema/aor_20141023.dtd">

<transcription xmlns:xsi="http://www.w3.org/2001/XMLSchema-instance"
    xsi:noNamespaceSchemaLocation="http://www.livesandletters.ac.uk/schema/aor2_18112016.xsd">
    <page filename="211.tif" reader="John Dee" pagination="96"/>
    <annotation>
                
        <marginalia hand="English_secretary">
            <language ident="LA">
                <position place="left_margin" book_orientation="0">
                    <marginalia_text>Cur gradus vnus anu[m] significauit,</marginalia_text> 
                </position>
            </language>
            <translation>When a degree signified one year.</translation>
        </marginalia>
        
        <underline method="pen" type="straight" language="LA" text="igitur Sol multiplicet partem quam in die pertransit, in id quod p[er]transit in anno"/>
        
        <errata language="LA" copytext="20" amendedtext="12"/>
        <errata language="LA" copytext="12" amendedtext="20"/>
        
        <drawing type="manicule" book_orientation="0" place="left_margin" method="pen" anchor_text="igitur Sol multiplicet partem quam in die pertransit, in id quod p[er]transit in anno"/>
        
        <table type="standard_table" place="intext">
            <tr>
                <td>31</td>
            </tr>
            <tr>
                <td>28</td>
            </tr>
            <tr>
                <td>31</td>
            </tr>
            <tr>
                <td>30</td>
            </tr>
            <tr>
                <td>31</td>
            </tr>
            <tr>
                <td>30</td>
            </tr>
            <tr>
                <td>31</td>
            </tr>
            <tr>
                <td>31</td>
            </tr>
            <tr>
                <td>30</td>
            </tr>
            <tr>
                <td>31</td>
            </tr>
            <tr>
                <td>30</td>
            </tr>
            <tr>
                <td>31</td>
            </tr>
        </table>
        
    </annotation>
</transcription>