<?xml version="1.0" encoding="UTF-8"?>
<!DOCTYPE transcription SYSTEM "http://www.livesandletters.ac.uk/schema/aor_20141023.dtd">

<transcription xmlns:xsi="http://www.w3.org/2001/XMLSchema-instance"
    xsi:noNamespaceSchemaLocation="http://www.livesandletters.ac.uk/schema/aor2_18112016.xsd">
    <page filename="493.tif" reader="John Dee" pagination="237" signature="OO"/>
    <annotation>
        
        <marginalia hand="English_secretary">
            <language ident="LA">
                <position place="right_margin" book_orientation="0">
                    <marginalia_text>Luminariu[m] opus res manifestare, et ad actu[m] p[er]duce[t]</marginalia_text>
                </position>
            </language>
            <translation>To clarify the matters of the works of lights even will lead to the act.</translation> 
        </marginalia>
        
        <marginalia hand="English_secretary">
            <language ident="LA">
                <position place="intext" book_orientation="0">
                    <marginalia_text>more italico ab occasu &Sun; co[m]putando</marginalia_text>
                    <symbol_in_text name="Sun"/>
                </position>
            </language>
            <translation>In the Italian way, by computing the setting of the Sun.</translation>
        </marginalia>
        
        <symbol name="Trine" place="intext"/>
        <symbol name="Trine" place="intext"/>
        <symbol name="Trine" place="intext"/>
        <symbol name="Sextile" place="intext"/>
        
        <mark name="vertical_bar" method="pen" place="intext"/>
        <mark name="vertical_bar" method="pen" place="intext"/>
        <mark name="vertical_bar" method="pen" place="intext"/>
        <mark name="vertical_bar" method="pen" place="intext"/>
        
        <mark name="horizontal_bar" method="pen" place="intext"/>
        <mark name="horizontal_bar" method="pen" place="intext"/>
        <mark name="horizontal_bar" method="pen" place="intext"/>
        <mark name="horizontal_bar" method="pen" place="intext"/>
        <mark name="horizontal_bar" method="pen" place="intext"/>
        
        <!--JG: How to capture these lines (for physical links need concrete reader interventions which can be linked together (but do not exist in this case!-->
        
    </annotation>
</transcription>