<?xml version="1.0" encoding="UTF-8" standalone="no"?>

<!DOCTYPE transcription SYSTEM "http://www.livesandletters.ac.uk/schema/aor_20141023.dtd">

<transcription xmlns:xsi="http://www.w3.org/2001/XMLSchema-instance"
    xsi:noNamespaceSchemaLocation="http://www.livesandletters.ac.uk/schema/aor_20141118.xsd">
    
    <page filename="earbm_stc_11402_0095.tif" reader="Harvey"  signature="[Eiiii[v]]"/>
    <annotation>
        
        <marginalia hand="Italian">
            <language ident="EN">
                <position place="head" book_orientation="0">
                    <marginalia_text>[the] order of Annibal, &amp; Scipio, in that most famous battel betwene them.</marginalia_text>
                    <person name="Hannibal"/>
                    <person name="Scipio Africanus"/>
                </position>
            </language>
        </marginalia>
        
        <marginalia hand="Italian">
            <language ident="EN">
                <position place="left_margin" book_orientation="0">
                    <marginalia_text>rerewarde.</marginalia_text>
                </position>
            </language>
        </marginalia>
        
        <marginalia hand="Italian">
            <language ident="EN">
                <position place="left_margin" book_orientation="0">
                    <marginalia_text>Scipios order better, in [the] vaward. [the] place of most valorous and furious bravure.</marginalia_text>
                    <person name="Scipio Africanus"/>
                </position>
            </language>
            <language ident="LA">
                <position place="left_margin" book_orientation="0">
                    <marginalia_text>s[upr]a)</marginalia_text>
                    <internal_ref text="s[upr]a">
                        <target filename="earbm_stc_11402_0090.xml" book_id="HoughtonSTC11402" text="[Eii[r]]"/>
                    </internal_ref>
                </position>
            </language>
            <translation>[See] above.</translation>
        </marginalia>
        
        <underline method="pen" type="straight" language="EN" text="Romaynes weried"/>
        <underline method="pen" type="straight" language="EN" text="myddell warde"/>
        <underline method="pen" type="straight" language="EN" text="laste of all"/>
        <underline method="pen" type="straight" language="EN" text="Italians"/>
        <underline method="pen" type="straight" language="EN" text="ageynste theyr wylles"/>
        <underline method="pen" type="straight" language="EN" text="strengthe of his legion"/>
        <underline method="pen" type="straight" language="EN" text="in thre"/>
        <underline method="pen" type="straight" language="EN" text="the front"/>
        <underline method="pen" type="straight" language="EN" text="chiefe and strongeste souldiours"/>
        <underline method="pen" type="straight" language="EN" text="lefte a space betwene"/>
        <underline method="pen" type="straight" language="EN" text="elephantes dryuen by"/>
        <underline method="pen" type="straight" language="EN" text="myght easely passe"/>
        <underline method="pen" type="straight" language="EN" text="troublynge or breakinge the order of his"/>
        <underline method="pen" type="straight" language="EN" text="eyther recule backe"/>
        <underline method="pen" type="straight" language="EN" text="go a syde"/>
        <underline method="pen" type="straight" language="EN" text="horsemen"/>
        <underline method="pen" type="straight" language="EN" text="the wynges"/>
        <underline method="pen" type="straight" language="EN" text="Romayne horsemen"/>
        <underline method="pen" type="straight" language="EN" text="Lelius"/>
        <underline method="pen" type="straight" language="EN" text="Masinissa ouer"/>
        
        <symbol name="Mars" place="left_margin" language="EN" text="[the] order of Annibal, &amp; Scipio, in that most famous battle betwene them."/>
        <symbol name="Opposite_planets" place="left_margin"/>
        
        <symbol name="SS" place="right_margin"/>
        
        <mark name="vertical_bar" method="pen" place="left_margin"/>
        <mark name="vertical_bar" method="pen" place="left_margin"/>
        <mark name="plus_sign" method="pen" place="left_margin"/>
        
        <mark name="plus_sign" method="pen" place="head" language="EN" text="Romaynes weried"/>
        
        <mark name="vertical_bar" method="chalk" place="intext"/>
        <mark name="vertical_bar" method="pen" place="intext"/> <!--wylles. Scipio-->
        <mark name="plus_sign" method="pen" place="intext" language="EN" text="strengthe"/>
        <mark name="plus_sign" method="pen" place="intext" language="EN" text="in thre"/>
        <mark name="dot" method="pen" place="intext"/> <!--batayles, in-->
        <mark name="plus_sign" method="pen" place="intext" language="EN" text="the front"/>
        <mark name="plus_sign" method="pen" place="intext" language="EN" text="chiefe and strongeste souldiours"/>
        <mark name="vertical_bar" method="chalk" place="intext"/>
        <mark name="bracket" method="pen" place="intext"/> <!--souldiours: he-->
        <mark name="bracket" method="pen" place="intext"/> <!--syde. farther-->
        
    </annotation>
</transcription>
