<?xml version="1.0" encoding="UTF-8"?>
<!DOCTYPE transcription SYSTEM "http://www.livesandletters.ac.uk/schema/aor_20141023.dtd">

<transcription xmlns:xsi="http://www.w3.org/2001/XMLSchema-instance"
    xsi:noNamespaceSchemaLocation="http://www.livesandletters.ac.uk/schema/aor2_18112016.xsd">
    <page filename="395.tif" reader="John Dee" pagination="389" signature="B 3"/> 
    <annotation>
        
        <!-- M.B. Greek marginalia to be added later -->
        
        <marginalia hand="Italian" anchor_text="signum">
            <language ident="LA">
                <position place="right_margin" book_orientation="0">
                    <marginalia_text>signum</marginalia_text>
                </position>
            </language>
            <translation>Sign.</translation>
        </marginalia>
        
        <marginalia hand="Italian" anchor_text="hypallagen">
            <language ident="LA">
                <position place="right_margin" book_orientation="0">
                    <marginalia_text>hypallage.</marginalia_text>
                </position>
            </language>
            <translation>Hypallage.</translation>
        </marginalia>
        
        <marginalia hand="Italian" anchor_text="fori seueritas">
            <language ident="LA">
                <position place="right_margin" book_orientation="0">
                    <marginalia_text>fori seueritas</marginalia_text>
                </position>
            </language>
            <translation>Seriousness of the vote.</translation>
        </marginalia>
        
        <marginalia hand="Italian" anchor_text="possessore">
            <language ident="LA">
                <position place="right_margin" book_orientation="0">
                    <marginalia_text>Po&sharp-S;e&sharp-S;or.</marginalia_text>
                </position>
            </language>
            <translation>Possessor.</translation>
        </marginalia>
        
        <underline method="pen" type="straight" language="LA" text="[ser]monis, quod tacetur, accipimus"/>
        <underline method="pen" type="straight" language="LA" text="inuentore, &amp; subiecta ab obstinentibus significat: ut"/>
        <underline method="pen" type="straight" language="LA" text="inquantum"/>
        <underline method="pen" type="straight" language="LA" text="quod continet, id quod continetur, usus recipit, ut"/>
        <underline method="pen" type="straight" language="LA" text="est, raro audeat quis nisi po&euml;ta"/>
        <underline method="pen" type="straight" language="LA" text="potius est &agrave; possessore quod po&sharp-S;idetur, ut"/>
        <underline method="pen" type="straight" language="LA" text="quo eum qui efficit, ex eo quod"/>
        
        <mark name="bracket" method="pen" place="right_margin"/>
        <mark name="tripunctus" method="pen" place="right_margin"/>
        
    </annotation>
</transcription>