<?xml version="1.0" encoding="UTF-8" standalone="no"?>

<!DOCTYPE transcription SYSTEM "http://www.livesandletters.ac.uk/schema/aor_20141023.dtd">

<transcription xmlns:xsi="http://www.w3.org/2001/XMLSchema-instance"
    xsi:noNamespaceSchemaLocation="http://www.livesandletters.ac.uk/schema/aor_20141118.xsd">
    
<page filename="00000186.tif" reader="Harvey" pagination="[45v]" signature="M.i.v"/>
    <annotation>
        
        <underline method="pen" type="straight" language="LA" text="Nam copia[m] &amp; vbertatem habere difficillimum est, egestatem"/>
        <underline method="pen" type="straight" language="LA" text="&amp; inopiam, &amp; paupertate[m], &amp; famem, &amp; omnino"/>
        <underline method="pen" type="straight" language="LA" text="vbertas ad esurie[m] decoquetur"/>
        <underline method="pen" type="straight" language="LA" text="fames ad saturitate[m] perducetur"/>
        <underline method="pen" type="straight" language="LA" text="Latinae quoque lingua[e]"/>
        <underline method="pen" type="straight" language="LA" text="non correximus"/>
        <underline method="pen" type="straight" language="LA" text="vni laboranti medicus gratis subveniret"/>
        <underline method="pen" type="straight" language="LA" text="qu&ograve;d hic sanabatur gratias non aget"/>
        <underline method="pen" type="straight" language="LA" text="qu&ograve;d alter a[e]grotat medico dicam impingit"/>
        
        <symbol name="Mercury" place="left_margin"/>
        
        <mark name="vertical_bar" method="chalk" place="intext"/> <!-- Lati- Quid po- -->
        <mark name="plus_sign" method="pen" place="left_margin"/>
        <mark name="dot" method="pen" place="intext"/> <!-- above 'minus' -->
        
    </annotation>
</transcription>
