<?xml version="1.0" encoding="UTF-8"?>
<!DOCTYPE transcription SYSTEM "http://www.livesandletters.ac.uk/schema/aor_20141023.dtd">

<transcription xmlns:xsi="http://www.w3.org/2001/XMLSchema-instance"
    xsi:noNamespaceSchemaLocation="http://www.livesandletters.ac.uk/schema/aor2_18112016.xsd">
    <page filename="778.tif" reader="John Dee" pagination="312"/>
    <annotation>
        
        <marginalia hand="Italian" anchor_text="Richardus de Clare, Comes illustris Glocestriae &amp; Herefordiae, circa hoc tempus obijt">
            <language ident="LA">
                <position place="left_margin" book_orientation="0">
                    <marginalia_text>
                        Obitus Richardi de Clare Comitis glocest et Hertf.
                    </marginalia_text>
                    <person name="Richard de Clare, 6th Earl of Gloucester"/>                   
                </position>
            </language>
            <translation>
                Death of Richard de Clare, 6th Earl of Gloucester, [5th] Earl of Hertford.
            </translation>
        </marginalia>
        
        <marginalia hand="Italian" anchor_text="Rogerij de Mortuo mari">
            <language ident="LA">
                <position place="left_margin" book_orientation="0">
                    <marginalia_text>
                        Rogerus de M. M
                    </marginalia_text>
                    <person name="Roger Mortimer, 1st Baron Mortimer"/>
                </position>
            </language>
            <translation>
                Roger Mortimer, 1st Baron Mortimer.
            </translation>
        </marginalia>
        
        <marginalia hand="Italian" anchor_text="marchionibus peditibus">
            <language ident="EN">
                <position place="left_margin" book_orientation="0">
                    <marginalia_text>
                        foremen of the Marches.    <!-- DO: I think it might say 'fotemen' (as in footmen); matches more closely with 'peditibus' -->
                    </marginalia_text>
                </position>
            </language>
        </marginalia>
        
        <underline method="pen" type="straight" language="LA" text="Baldevvinus de insula, Comes Deuoniae"/>
        <underline method="pen" type="straight" language="LA" text="Et Richardus de Clare, Comes illustris Glocestriae &amp; Herefordiae"/>
        <underline method="pen" type="straight" language="LA" text="tempus obijt in Cantia &amp;"/>
        <underline method="pen" type="double" language="LA" text="sepultus est apud Thekesburie"/>
        <underline method="pen" type="straight" language="LA" text="vitute ac morum praerogatiua, sic de eo illic haeroic&egrave; intitulatur"/>
        <underline method="pen" type="straight" language="LA" text="Hic pudor Hippoliti"/>
        <underline method="pen" type="straight" language="LA" text="Paridis gena"/>
        <underline method="pen" type="straight" language="LA" text="sensus Vli&sharp-S;is Aeneae pietas"/>
        <underline method="pen" type="straight" language="LA" text="Hectoris ira iacet"/>
        <underline method="pen" type="straight" language="LA" text="suo principe Leolino, de suis sedibus irrumpentes, terras"/>
        <underline method="pen" type="straight" language="LA" text="Mortuo mari hostiliter inuadunt"/>
        <underline method="pen" type="straight" language="LA" text="Rogerius igitur"/>
        <underline method="pen" type="double" language="LA" text="mari, fama dignus"/>
        <underline method="pen" type="straight" language="LA" text=".ccc"/>
        <underline method="pen" type="straight" language="LA" text="marchionibus peditibus"/>
        
        <mark name="circumflex" method="pen" place="intext"/>              <!-- DO: Bracket in left margin -->
        
        <errata language="LA" copytext="midio" amendedtext="medio"/>
        
    </annotation>
</transcription>