<?xml version="1.0" encoding="UTF-8"?>

<!DOCTYPE transcription SYSTEM "http://www.livesandletters.ac.uk/schema/aor_20141023.dtd">

<transcription xmlns:xsi="http://www.w3.org/2001/XMLSchema-instance"
    xsi:noNamespaceSchemaLocation="http://www.livesandletters.ac.uk/schema/aor2_18112016.xsd">
    <page filename="015.tif" reader="John Dee" signature="[Aiij[v]]"/> 
    <annotation>
        
        <marginalia hand="Italian" anchor_text="positione[m] namq[uam] qua[n]da[m] p[er]manentia[m] c[on]tinuitat[is] ordine[m] vero quanda[m] inp[er]manentia[m] sep[ar]atio[n]is">
            <language ident="LA">
                <position place="right_margin" book_orientation="0">
                    <marginalia_text>
                        Positio. ordo
                    </marginalia_text>
                </position>
            </language>
            <translation>
                Position. Order.
            </translation>
        </marginalia>
        
        <marginalia hand="Italian" anchor_text="p[ar]tib[us] aliquotis">
            <language ident="LA">
                <position place="right_margin" book_orientation="0">
                    <marginalia_text>
                        Partes aliq[uo]tae
                    </marginalia_text>
                </position>
            </language>
            <translation>
                As many other parts.
            </translation>
        </marginalia>
        
        <marginalia hand="Italian">
            <language ident="LA">
                <position place="right_margin" book_orientation="0">
                    <marginalia_text>
                        obiectio solutio.
                    </marginalia_text>
                </position>
            </language>
           <translation>
               Objection, solution.
           </translation>
        </marginalia>
        
        <marginalia hand="Italian" anchor_text="Causam p[ro]pter q[ui]d">
            <language ident="LA">
                <position place="right_margin" book_orientation="0">
                    <marginalia_text>
                        Causa p[ro]pter q[ui]d
                    </marginalia_text>
                </position>
            </language>
            <translation>
                The cause for which.
            </translation>
        </marginalia>
        
        <underline method="pen" type="straight" language="LA" text="positione[m]"/>
        <underline method="pen" type="straight" language="LA" text="ordine[m] vero"/>
        <underline method="pen" type="straight" language="LA" text="p[ar]tib[us] aliquotis"/>
        <underline method="pen" type="straight" language="LA" text="ei[us] no[n] copulant[ur] p[er] illu[m] terminu[m] tanq[uam] per modu[m] p[ri]ncipij [et] finis"/>
        <underline method="pen" type="straight" language="LA" text="[et] quinta quare vnitates eq[ui]uocant[ur] s[ecundu]m substa[n]tia[m] nu[m]eri q[uo]d semel"/>
        <underline method="pen" type="straight" language="LA" text="Sed in equiuocis quid co[mmun]e no[n] reperit[ur] sed in vniuocis"/>
        <underline method="pen" type="straight" language="LA" text="p[ro]pter quid"/>
        
        <mark name="comma" method="pen" place="intext"/> <!-- ordinem distinctim -->
        
    </annotation>
</transcription>