<?xml version="1.0" encoding="UTF-8" standalone="no"?>

<!DOCTYPE transcription SYSTEM "http://www.livesandletters.ac.uk/schema/aor_20141023.dtd">

<transcription xmlns:xsi="http://www.w3.org/2001/XMLSchema-instance"
    xsi:noNamespaceSchemaLocation="http://www.livesandletters.ac.uk/schema/aor_20141118.xsd">
    
    <page filename="00000537.tif" reader="Harvey" pagination="531"/>
    <annotation>
        
        <marginalia hand="Italian">
            <language ident="LA">
                <position place="head" book_orientation="0">
                    <marginalia_text>
                        Cyri pa[e]dja.
                    </marginalia_text>
                    <person name="Cyrus the Great"/>
                </position>
            </language>
            <translation>
                Cyrus' learning.
            </translation>
        </marginalia>
        
        <marginalia hand="Italian">
            <language ident="LA">
                <position place="head" book_orientation="0">
                    <marginalia_text>
                        Pa[e]dagogia. Prudens.
                    </marginalia_text>
                    <emphasis method="pen" type="straight" text="Pa[e]dagogia. Prudens."/>
                </position>
            </language>
            <translation>
                Pedagogy. Prudent.
            </translation>
        </marginalia>
                
        <underline method="pen" type="straight" language="LA" text="medicinales planta[e]"/>
        <underline method="pen" type="straight" language="LA" text="generosa virtus verbo"/>
        <underline method="pen" type="straight" language="LA" text="imponi pulchra nomina"/>
        <underline method="pen" type="straight" language="LA" text="s[a]epius eosde[m] interrogari"/>
        <underline method="pen" type="straight" language="LA" text="in cleri militiam ascribantur"/>
        <underline method="pen" type="straight" language="LA" text="ab Episcopo, vel praesidente locorum"/>
        <underline method="pen" type="straight" language="LA" text="magistri, seu p[a]edotrib[a]e"/>
        <underline method="pen" type="straight" language="LA" text="ducentos, trecentosq[ue] diuersarum [a]etatum"/>
        <underline method="pen" type="straight" language="LA" text="etia[m]si filii principum sint"/>
        <underline method="pen" type="straight" language="LA" text="adhibita virga &amp; ferula"/>
        <underline method="pen" type="straight" language="LA" text="ni probi esse"/>
        <underline method="pen" type="straight" language="LA" text="corripiant"/>
        <underline method="pen" type="straight" language="LA" text="tanquam bestias flagris"/>
        <underline method="pen" type="straight" language="LA" text="equos calcaribus ad cursum"/>
        <underline method="pen" type="straight" language="LA" text="enim licentiose&egrave;"/>
        <underline method="pen" type="straight" language="LA" text="pueros educat in vitiis"/>
        <underline method="pen" type="straight" language="LA" text="fures eosdem plectendos"/>
        <underline method="pen" type="straight" language="LA" text="lugebit in patibulis"/>
        <underline method="pen" type="straight" language="LA" text="disciplin[a]e scholastic[a]e"/>
        <underline method="pen" type="straight" language="LA" text="egregia indoles"/>
        <underline method="pen" type="straight" language="LA" text="eximium ingenium"/>
        <underline method="pen" type="straight" language="LA" text="animus ad bonas artes, &amp; scientias propensior"/>
        <underline method="pen" type="straight" language="LA" text="ad addiscendum peregrinas linguas"/>
        <underline method="pen" type="straight" language="LA" text="propter fideliorem interpretationem scripturarum"/>
        <underline method="pen" type="straight" language="LA" text="inaestimabilem"/>
        <underline method="pen" type="straight" language="LA" text="iacturam amissorum"/>
        <underline method="pen" type="straight" language="LA" text="Musicae, ac Astronomicae"/>
        <underline method="pen" type="straight" language="LA" text="Arithmeticae facultati"/>
        <underline method="pen" type="straight" language="LA" text="ac Geometricae arti vehementer incumbunt"/>
        <underline method="pen" type="straight" language="LA" text="Geometricae expers ingrediatur"/>
        <underline method="pen" type="straight" language="LA" text="etiam affectuum debita mensura"/>
        <underline method="pen" type="straight" language="LA" text="Ho[c] diuina p[ro]uidentia"/> 
        <underline method="pen" type="straight" language="LA" text="Iuuenes atte[n]tissim&egrave; educa[n]di."/>
        <underline method="pen" type="straight" language="LA" text="No[v]ia pulchra. Pueri s[a]epius interrogandi."/>
        <underline method="pen" type="straight" language="LA" text="P[a]edotrib[a]e. Filii principu[m] sub ferula."/>
        <underline method="pen" type="straight" language="LA" text="Adolesce[n]tes his artibus incumbunt."/>
        
        <mark name="plus_sign" method="pen" place="head"/>
        
        <mark name="plus_sign" method="pen" place="intext" language="LA" text="etia[n]si filii principum sint"/>
        <mark name="plus_sign" method="pen" place="intext" language="LA" text="tanquam"/>
        <mark name="plus_sign" method="pen" place="intext" language="LA" text="ad addiscendum peregrinas linguas"/>
        
    </annotation>
</transcription>